rosros/__init__.py
rosros/api.py
rosros/core.py
rosros/parsing.py
rosros/patch.py
rosros/ros1.py
rosros/ros2.py
rosros/util.py
rosros/rclify/__init__.py
rosros/rclify/callback_groups.py
rosros/rclify/clock.py
rosros/rclify/duration.py
rosros/rclify/exceptions.py
rosros/rclify/executors.py
rosros/rclify/node.py
rosros/rclify/parameter.py
rosros/rclify/qos.py
rosros/rclify/rclify.py
rosros/rclify/task.py
rosros/rclify/time.py
rosros/rclify/topic_endpoint_info.py
rosros/rospify/__init__.py
rosros/rospify/client.py
rosros/rospify/core.py
rosros/rospify/exceptions.py
rosros/rospify/log.py
rosros/rospify/msg.py
rosros/rospify/msproxy.py
rosros/rospify/names.py
rosros/rospify/rospify.py
rosros/rospify/rostime.py
rosros/rospify/service.py
rosros/rospify/timer.py
rosros/rospify/topics.py
rosros-0.2.6.dist-info/LICENSE.md
rosros-0.2.6.dist-info/METADATA
rosros-0.2.6.dist-info/WHEEL
rosros-0.2.6.dist-info/top_level.txt
rosros-0.2.6.dist-info/RECORD
