Metadata-Version: 2.1
Name: rosros
Version: 0.2.6
Summary: Simple unified interface to ROS1 / ROS2 Python API
Home-page: https://github.com/suurjaak/rosros
Author: Erki Suurjaak
Author-email: erki@lap.ee
License: BSD
Keywords: ROS ROS1 ROS2
Platform: any
Classifier: Development Status :: 4 - Beta
Classifier: License :: OSI Approved :: BSD License
Classifier: Intended Audience :: Developers
Classifier: Operating System :: POSIX
Classifier: Topic :: Scientific/Engineering
Classifier: Topic :: Utilities
Classifier: Programming Language :: Python :: 3
Requires-Python: >=3
Requires-Dist: pyyaml
